s2/__init__.py
s2/api.py
s2/models.py
s2/db/__init__.py
s2/db/json.py
pys2-1.1.0.dist-info/AUTHORS.rst
pys2-1.1.0.dist-info/LICENSE.txt
pys2-1.1.0.dist-info/METADATA
pys2-1.1.0.dist-info/WHEEL
pys2-1.1.0.dist-info/top_level.txt
pys2-1.1.0.dist-info/RECORD
