Metadata-Version: 2.1
Name: pys2
Version: 1.1.0
Summary: PyS2  is a python wrapper for the Semantic Scholar (S2) API
Home-page: https://github.com/mirandrom/pys2/
Author: mirandrom
License: UNKNOWN
Project-URL: Bug Reports, https://github.com/mirandrom/pys2/issues
Project-URL: Source, https://github.com/mirandrom/pys2/
Project-URL: Docs, https://pys2.readthedocs.org/
Keywords: semantic scholar,s2,scientific literature,citation graph
Platform: UNKNOWN
Classifier: Development Status :: 4 - Beta
Classifier: Intended Audience :: Developers
Classifier: Intended Audience :: Science/Research
Classifier: License :: OSI Approved :: MIT License
Classifier: Natural Language :: English
Classifier: Operating System :: OS Independent
Classifier: Programming Language :: Python
Classifier: Programming Language :: Python :: 3
Classifier: Programming Language :: Python :: 3.6
Classifier: Programming Language :: Python :: 3.7
Classifier: Programming Language :: Python :: 3.8
Classifier: Programming Language :: Python :: 3.9
Classifier: Topic :: Utilities
Requires-Python: >=3.6, <4
Requires-Dist: requests (<3.0,>=2.6)
Requires-Dist: pydantic (<2.0,>=1.8)
Provides-Extra: readthedocs
Requires-Dist: sphinx (<4.0,>=3) ; extra == 'readthedocs'
Provides-Extra: test
Requires-Dist: betamax (<0.9,>=0.8) ; extra == 'test'
Requires-Dist: pytest (<7,>=6) ; extra == 'test'
